appicon/__init__.py
appicon/icongen.py
appicon/android/Contents.json
appicon/android/__init__.py
appicon/android/androidicongen.py
appicon/ios/Contents.json
appicon/ios/__init__.py
appicon/ios/iosicongen.py
appicon-1.1.5.dist-info/LICENSE
appicon-1.1.5.dist-info/METADATA
appicon-1.1.5.dist-info/WHEEL
appicon-1.1.5.dist-info/top_level.txt
appicon-1.1.5.dist-info/RECORD
